{"type": "minecraft:crafting_shaped", "category": "building", "show_notification": true, "key": {"#": {"item": "crimson_planks"}, "$": {"item": "crimson_fence"}, "%": {"item": "stick"}}, "pattern": ["###", "$"], "result": {"count": 1, "id": "minecraft:firework_star", "components": {"minecraft:item_name": [{"text": "\u5355\u817f\u7eef\u7ea2\u83cc\u6728\u677f\u684c"}], "minecraft:custom_model_data": "18014", "minecraft:custom_data": {"nw_fur_id": 726}, "minecraft:firework_explosion": {"shape": "small_ball", "colors": [16777215]}}}, "group": "nw:table_plank_oneleg"}